ghga_transpiler/__init__.py
ghga_transpiler/__main__.py
ghga_transpiler/cli.py
ghga_transpiler/core.py
ghga_transpiler/io.py
ghga_transpiler/transformations.py
ghga_transpiler/config/__init__.py
ghga_transpiler/config/config.py
ghga_transpiler/config/exceptions.py
ghga_transpiler/configs/0.10.yaml
ghga_transpiler/configs/1.0.yaml
ghga_transpiler/configs/1.1.yaml
ghga_transpiler/configs/2.0.yaml
ghga_transpiler/configs/2.1.yaml
ghga_transpiler/configs/__init__.py
ghga_transpiler-2.3.2.dist-info/licenses/LICENSE
ghga_transpiler-2.3.2.dist-info/METADATA
ghga_transpiler-2.3.2.dist-info/WHEEL
ghga_transpiler-2.3.2.dist-info/entry_points.txt
ghga_transpiler-2.3.2.dist-info/top_level.txt
ghga_transpiler-2.3.2.dist-info/RECORD
