Metadata-Version: 2.4
Name: ghga_transpiler
Version: 2.3.2
Summary: GHGA-Transpiler - excel to JSON converter
Author-email: "German Human Genome Phenome Archive (GHGA)" <contact@ghga.de>
License: Apache 2.0
Project-URL: Repository, https://github.com/ghga-de/ghga-transpiler
Classifier: Development Status :: 1 - Planning
Classifier: Operating System :: POSIX :: Linux
Classifier: Programming Language :: Python :: 3
Classifier: Programming Language :: Python :: 3.12
Classifier: License :: OSI Approved :: Apache Software License
Classifier: Topic :: Internet :: WWW/HTTP :: HTTP Servers
Classifier: Topic :: Software Development :: Libraries
Classifier: Intended Audience :: Developers
Requires-Python: >=3.9
License-File: LICENSE
Requires-Dist: typer>=0.12
Requires-Dist: openpyxl==3.*,>=3.1.2
Requires-Dist: defusedxml==0.*,>=0.7
Requires-Dist: pydantic<3,>=2.6
Requires-Dist: PyYAML~=6.0
Requires-Dist: semver==3.*
Requires-Dist: click~=8.1.0
Dynamic: license-file
